Metadata-Version: 1.1
Name: cognito-search
Version: 0.0.1
Summary: A CLI to easily search for Cognito user pools
Home-page: https://github.com/abaltra/cognito-search
Author: Alejandro Baltra
Author-email: abaltra@gmail.com
License: MIT
Keywords: aws-cognito-idp,cognito,user-pools
Platform: UNKNOWN
Classifier: Intended Audience :: Developers
Classifier: Natural Language :: English
Classifier: License :: OSI Approved :: MIT License
Classifier: Programming Language :: Python
Classifier: Programming Language :: Python :: 2
Classifier: Programming Language :: Python :: 2.7
Classifier: Programming Language :: Python :: 3
Classifier: Programming Language :: Python :: 3.6
